{
  "db_name": "PostgreSQL",
  "query": "INSERT INTO users (id, email, password_hash) VALUES ($1, $2, $3) RETURNING *",
  "describe": {
    "columns": [
      {
        "ordinal": 0,
        "name": "id",
        "type_info": "Uuid"
      },
      {
        "ordinal": 1,
        "name": "email",
        "type_info": "Text"
      },
      {
        "ordinal": 2,
        "name": "password_hash",
        "type_info": "Text"
      },
      {
        "ordinal": 3,
        "name": "created_at",
        "type_info": "Timestamptz"
      },
      {
        "ordinal": 4,
        "name": "username",
        "type_info": "Text"
      },
      {
        "ordinal": 5,
        "name": "avatar_url",
        "type_info": "Text"
      },
      {
        "ordinal": 6,
        "name": "bio",
        "type_info": "Text"
      },
      {
        "ordinal": 7,
        "name": "country",
        "type_info": "Bpchar"
      }
    ],
    "parameters": {
      "Left": [
        "Uuid",
        "Text",
        "Text"
      ]
    },
    "nullable": [
      false,
      false,
      true,
      false,
      true,
      true,
      true,
      true
    ]
  },
  "hash": "3a139ab41e70266ab6a4860bcd460f464c62c6b2ef8ae25646c1b37395ac0c88"
}
